Metadata-Version: 2.1
Name: colourful-console
Version: 1.0.1
Summary: A simple python package to print colors in terminal using simple markup syntax
Home-page: https://github.com/sirshakbohara/colourful-console
Author: Sirshak Bohara
Author-email: 021neb459@sxc.edu.np
License: MIT
Project-URL: Bug Tracker, https://github.com/sirshakbohara/colourful-console/issues
Keywords: python color,console color,terminal colors,markdown colors
Platform: UNKNOWN
Classifier: Programming Language :: Python :: 3
Classifier: License :: OSI Approved :: MIT License
Classifier: Operating System :: OS Independent
Requires-Python: >=3.6
License-File: LICENSE
